kn_flatten_json/__init__.py
kn_flatten_json/kn_flatten_json.py
kn_flatten_json-0.0.10.dist-info/LICENSE
kn_flatten_json-0.0.10.dist-info/METADATA
kn_flatten_json-0.0.10.dist-info/WHEEL
kn_flatten_json-0.0.10.dist-info/top_level.txt
kn_flatten_json-0.0.10.dist-info/RECORD
