Metadata-Version: 2.1
Name: kn-flatten-json
Version: 0.0.10
Summary: kn_flatten_json
Home-page: UNKNOWN
Author: Sukriti
Author-email: sukriti.saluja@kockpit.in
License: UNKNOWN
Keywords: flatten,json,normalize,normalize pyspark dataframe,complex datatypes,flatten dataframe
Platform: UNKNOWN
Classifier: Development Status :: 1 - Planning
Classifier: Intended Audience :: Developers
Classifier: Programming Language :: Python :: 3
Classifier: Operating System :: Unix
Classifier: Operating System :: MacOS :: MacOS X
Classifier: Operating System :: Microsoft :: Windows
License-File: LICENSE
